deepbrief/__init__.py
deepbrief/_version.py
deepbrief/app.py
deepbrief/activities/__init__.py
deepbrief/activities/classify.py
deepbrief/activities/create_index.py
deepbrief/activities/download.py
deepbrief/activities/llm.py
deepbrief/activities/models.py
deepbrief/activities/podcast.py
deepbrief/activities/prompt.py
deepbrief/activities/read.py
deepbrief/activities/readv2.py
deepbrief/activities/search.py
deepbrief/activities/speak.py
deepbrief/services/__init__.py
deepbrief/services/storage.py
deepbrief/workflows/__init__.py
deepbrief/workflows/create_podcast.py
deepbrief/workflows/generate_episodes.py
deepbrief/workflows/generate_recordings.py
deepbrief/workflows/generate_transcripts.py
deepbrief/workflows/get_papers.py
deepbrief/workflows/models.py
deepbrief-0.1.0.dist-info/licenses/LICENSE
deepbrief-0.1.0.dist-info/METADATA
deepbrief-0.1.0.dist-info/WHEEL
deepbrief-0.1.0.dist-info/entry_points.txt
deepbrief-0.1.0.dist-info/top_level.txt
deepbrief-0.1.0.dist-info/RECORD
