Metadata-Version: 2.4
Name: deepbrief
Version: 0.1.0
Summary: A workflow-driven system for converting PDF documents into structured narrative and audio briefings.
Author-email: Roberto Rodriguez <9653181+Cyb3rWard0g@users.noreply.github.com>
License: Apache-2.0
Project-URL: Homepage, https://github.com/Cyb3rWard0g/deepbrief
Project-URL: Issues, https://github.com/Cyb3rWard0g/deepbrief/issues
Classifier: License :: OSI Approved :: Apache Software License
Classifier: Programming Language :: Python :: 3
Classifier: Programming Language :: Python :: 3.13
Requires-Python: >=3.13
License-File: LICENSE
Requires-Dist: dapr<1.17,>=1.16
Requires-Dist: dapr-ext-workflow<1.17,>=1.16
Requires-Dist: dapr-agents<0.11,>=0.10
Requires-Dist: fastapi<0.122,>=0.121
Requires-Dist: pypdf<7.0,>=6.2
Requires-Dist: pyyaml<7.0,>=6.0
Requires-Dist: arxiv<3.0,>=2.3
Requires-Dist: elevenlabs<3.0,>=2.22
Requires-Dist: pydub<0.26,>=0.25
Requires-Dist: python-dotenv<2.0,>=1.0
Requires-Dist: audioop-lts<0.3,>=0.2
Requires-Dist: uvicorn[standard]<0.39,>=0.38
Requires-Dist: docling<3.0,>=2.61
Provides-Extra: dev
Requires-Dist: pytest<9.0,>=8.4; extra == "dev"
Requires-Dist: pytest-asyncio<0.24,>=0.23; extra == "dev"
Requires-Dist: ruff<0.7,>=0.6; extra == "dev"
Requires-Dist: black<25.0,>=24.10; extra == "dev"
Requires-Dist: mypy<1.12,>=1.11; extra == "dev"
Requires-Dist: pytest-cov<6.0,>=5.0; extra == "dev"
Provides-Extra: release
Requires-Dist: build<2.0,>=1.2; extra == "release"
Requires-Dist: twine<6.0,>=5.0; extra == "release"
Requires-Dist: packaging<25.0,>=24.1; extra == "release"
Dynamic: license-file
